lava_test_plans/__init__.py
lava_test_plans/__main__.py
lava_test_plans/fastboot.jinja2
lava_test_plans/master.jinja2
lava_test_plans/nfs.jinja2
lava_test_plans/qemu.jinja2
lava_test_plans/utils.py
lava_test_plans/devices/bcm2711-rpi-4-b
lava_test_plans/devices/dragonboard-410c
lava_test_plans/devices/dragonboard-820c
lava_test_plans/devices/dragonboard-845c
lava_test_plans/devices/e850-96
lava_test_plans/devices/hi6220-hikey
lava_test_plans/devices/hi960-hikey
lava_test_plans/devices/i386
lava_test_plans/devices/juno
lava_test_plans/devices/juno-r2
lava_test_plans/devices/nxp-ls2088
lava_test_plans/devices/qcs404-evb-1k
lava_test_plans/devices/qcs404-evb-4k
lava_test_plans/devices/qemu_arm
lava_test_plans/devices/qemu_arm64
lava_test_plans/devices/qemu_i386
lava_test_plans/devices/qemu_x86_64
lava_test_plans/devices/qrb5165-rb5
lava_test_plans/devices/rzn1d
lava_test_plans/devices/sdm845-mtp
lava_test_plans/devices/sm8150-mtp
lava_test_plans/devices/sm8250-mtp
lava_test_plans/devices/sm8350-mtp
lava_test_plans/devices/soca9
lava_test_plans/devices/stm32mp157c-dk2
lava_test_plans/devices/synquacer
lava_test_plans/devices/thunderx
lava_test_plans/devices/x15
lava_test_plans/devices/x15-bl
lava_test_plans/devices/x86
lava_test_plans/devices/variables/x15.yaml
lava_test_plans/devices/variables/x86.yaml
lava_test_plans/include/fastboot.jinja2
lava_test_plans/include/test_target.jinja2
lava_test_plans/include/boot_target/auto_login.jinja2
lava_test_plans/include/boot_target/auto_login_commands.jinja2
lava_test_plans/include/boot_target/boot_os_prompt.jinja2
lava_test_plans/include/boot_target/post_boot_command.jinja2
lava_test_plans/include/boot_target/pre_boot_commands.jinja2
lava_test_plans/include/boot_target/pre_power_command.jinja2
lava_test_plans/include/boot_target/timeout_and_method.jinja2
lava_test_plans/include/boot_target/transfer_overlay.jinja2
lava_test_plans/projects/armnn/fastboot.jinja2
lava_test_plans/projects/armnn/nfs.jinja2
lava_test_plans-3.2.0.dist-info/entry_points.txt
lava_test_plans-3.2.0.dist-info/LICENSE
lava_test_plans-3.2.0.dist-info/WHEEL
lava_test_plans-3.2.0.dist-info/METADATA
lava_test_plans-3.2.0.dist-info/RECORD
