Metadata-Version: 2.1
Name: lava-test-plans
Version: 3.2.0
Summary: Generate LAVA job definitions for different devices and tests
Author-email: Anders Roxell <anders.roxell@linaro.org>
Classifier: License :: OSI Approved :: MIT License
Requires-Dist: configobj
Requires-Dist: docker
Requires-Dist: jinja2
Requires-Dist: requests
Requires-Dist: ruamel.yaml
Project-URL: Source, https://github.com/linaro/lava-test-plans
